langchain_polaris_ai_datainsight/__init__.py
langchain_polaris_ai_datainsight/datainsight_loader.py
langchain_polaris_ai_datainsight/py.typed
langchain_polaris_ai_datainsight-1.0.0.dist-info/LICENSE
langchain_polaris_ai_datainsight-1.0.0.dist-info/METADATA
langchain_polaris_ai_datainsight-1.0.0.dist-info/WHEEL
langchain_polaris_ai_datainsight-1.0.0.dist-info/RECORD
