Metadata-Version: 2.3
Name: langchain-polaris-ai-datainsight
Version: 1.0.0
Summary: An integration package connecting PODataInsight and LangChain
License: MIT
Author: Polaris Office
Author-email: ai@polarisoffice.com
Requires-Python: >=3.10,<4.0
Classifier: License :: OSI Approved :: MIT License
Classifier: Programming Language :: Python :: 3
Classifier: Programming Language :: Python :: 3.10
Classifier: Programming Language :: Python :: 3.11
Classifier: Programming Language :: Python :: 3.12
Classifier: Programming Language :: Python :: 3.13
Requires-Dist: langchain-core (>=0.3.15,<0.4.0)
Requires-Dist: polaris-ai-datainsight (>=1.0.0,<2.0.0)
Requires-Dist: python-dotenv (>=1.1.0,<2.0.0)
Project-URL: Source Code, https://github.com/PolarisOfficeRnD/PolarisAIDataInsight/langchain-polaris-ai-datainsight
